MANIFEST.in
README.md
ez_setup.py
setup.py
metaphor/__init__.py
metaphor/version_gm_test.py
metaphor/test_chem_gm/__init__.py
metaphor/test_chem_gm/__main__.py
metaphor/test_chem_gm/chem_gm_test.py
metaphor/test_chem_gm/main.py
metaphor/test_chem_gm/test_GMmodel.py
metaphor/test_chem_gm/test_cycles.py
metaphor/test_chem_gm/test_molecule.py
metaphor/test_chem_gm/test_phenol_smiles.py
metaphor/test_chem_gm/test_smiparser.py
metaphor/test_chem_gm/test_smiparser2.py
metaphor/test_chem_gm/test_stability_smiles.py
metaphor/test_chem_gm/test_token.py
metaphor/test_chem_gm/testfiles/B200-11RT.xlsx
metaphor/test_chem_gm/testfiles/BJMA269EMOL.xlsx
metaphor/test_chem_gm/testfiles/BJMA271EMOS.xlsx
metaphor/test_chem_gm/testfiles/Base10.csv
metaphor/test_chem_gm/testfiles/Base129RT_T427.xlsx
metaphor/test_chem_gm/testfiles/Base321.xlsx
metaphor/test_chem_gm/testfiles/Base321E_chem.xlsx
metaphor/test_chem_gm/testfiles/BaseA109.xlsx
metaphor/test_chem_gm/testfiles/L_153.csv
metaphor/test_chem_gm/testfiles/NCI_Problemes.txt
metaphor/test_chem_gm/testfiles/NCI_aug00_SMI.txt
metaphor/test_chem_gm/testfiles/PoidsNML10.nml
metaphor/test_chem_gm/testfiles/SmileCasTab-JLP.xlsx
metaphor/test_chem_gm/testfiles/SmileCasTabIso.txt
metaphor/test_chem_gm/testfiles/SmileCasXLS.xlsx
metaphor/test_chem_gm/testfiles/WW10.npy
metaphor/test_chem_gm/testfiles/mmc1deverrouillee.xlsx
metaphor/test_chem_gm/testfiles/phenol.xlsx
metaphor_gm_test.egg-info/PKG-INFO
metaphor_gm_test.egg-info/SOURCES.txt
metaphor_gm_test.egg-info/dependency_links.txt
metaphor_gm_test.egg-info/entry_points.txt
metaphor_gm_test.egg-info/not-zip-safe
metaphor_gm_test.egg-info/requires.txt
metaphor_gm_test.egg-info/top_level.txt